{
  "Employees": [
    {
      "firstName": "Romin",
      "lastName": "Iraniq",
      "phoneNumber": 408123456,
      "gender": "female",
      "emailAddress": "romin.k.irani@gmail.com",
      "joinedDate": "2019-07-04",
      "userId": 1,
      "id": 1
    },
    {
      "userId": 2,
      "id": 2,
      "firstName": "Neil",
      "lastName": "Irani",
      "phoneNumber": 4081111111,
      "gender": "male",
      "emailAddress": "neilrirani@gmail.com",
      "joinedDate": "2020-11-23"
    },
    {
      "userId": 3,
      "id": 3,
      "firstName": "Tom",
      "lastName": "Hanks",
      "gender": "male",
      "phoneNumber": 4082222222,
      "emailAddress": "tomhanks@gmail.com",
      "joinedDate": "2021-12-13"
    },
    {
      "userId": 4,
      "id": 4,
      "firstName": "Tomaa",
      "lastName": "Hanksaa",
      "gender": "male",
      "phoneNumber": 4082222222,
      "emailAddress": "tomhanks@gmail.com",
      "joinedDate": "2021-12-13"
    },
    {
      "firstName": "Akash",
      "lastName": "Rajput",
      "phoneNumber": 12345678,
      "gender": "Male",
      "emailAddress": "akash.rajput9@hotmail.com",
      "joinedDate": "2020-10-21",
      "id": 5
    }
  ],
  "Users": [
    {
      "id": "admin",
      "password": "admin",
      "isAdmin": true,
      "token": "asdadadas"
    },
    {
      "id": "standard",
      "password": "standard",
      "isAdmin": false,
      "token": "asdasdads"
    },
    {
      "id": "admin2",
      "isAdmin": true,
      "password": "admin2"
    }
  ]
}